<annotation>
	<folder>train</folder>
	<filename>knife_216.jpg</filename>
	<path>C:\Users\Alcasla\Universidad\Máster Ciencia de Datos\TFM\Armas\Stage5 SSD\Datasets\train\knife_216.jpg</path>
	<source>
		<database>Unknown</database>
	</source>
	<size>
		<width>740</width>
		<height>542</height>
		<depth>3</depth>
	</size>
	<segmented>0</segmented>
	<object>
		<name>knife</name>
		<pose>Unspecified</pose>
		<truncated>0</truncated>
		<difficult>0</difficult>
		<bndbox>
			<xmin>148</xmin>
			<ymin>170</ymin>
			<xmax>474</xmax>
			<ymax>319</ymax>
		</bndbox>
	</object>
</annotation>
