<annotation>
	<folder>monederohombre</folder>
	<filename>monedero_1040.jpg</filename>
	<path>C:\Nueva Base de datos\monederohombre\monedero_1040.jpg</path>
	<source>
		<database>Unknown</database>
	</source>
	<size>
		<width>516</width>
		<height>640</height>
		<depth>3</depth>
	</size>
	<segmented>0</segmented>
	<object>
		<name>monedero</name>
		<pose>Unspecified</pose>
		<truncated>0</truncated>
		<difficult>0</difficult>
		<bndbox>
			<xmin>175</xmin>
			<ymin>207</ymin>
			<xmax>336</xmax>
			<ymax>433</ymax>
		</bndbox>
	</object>
</annotation>
