<annotation>
  <folder>Definitiva</folder>
  <filename>pistol_1112.jpg</filename>
  <path>C:\Users\Rob\Desktop\Definitiva\pistol_1112.jpg.jpg</path>
  <source>
    <database>Unknown</database>
  </source>
  <size>
    <width>600</width>
    <height>400</height>
    <depth>3</depth>
  </size>
  <segmented>0</segmented>
  <object>
    <name>pistol</name>
    <pose>Unspecified</pose>
    <truncated>0</truncated>
    <difficult>0</difficult>
    <bndbox>
      <xmin>389</xmin>
      <ymin>72</ymin>
      <xmax>502</xmax>
      <ymax>269</ymax>
    </bndbox>
  </object>
</annotation>
