<annotation verified="no">
	<folder>Nueva carpeta (2)</folder>
	<filename>smartphone_0358.jpg</filename>
	<path>/home/fperez/Dropbox/zTrabajo/6 Refuerzo/3 Meter moviles en la BD/BuenaCalidad/Nueva carpeta (2)/smartphone_0358.jpg</path>
	<source>
		<database>Unknown</database>
	</source>
	<size>
		<width>1338</width>
		<height>906</height>
		<depth>3</depth>
	</size>
	<segmented>0</segmented>
	<object>
		<name>smartphone</name>
		<pose>Unspecified</pose>
		<truncated>0</truncated>
		<difficult>0</difficult>
		<bndbox>
			<xmin>328</xmin>
			<ymin>76</ymin>
			<xmax>997</xmax>
			<ymax>826</ymax>
		</bndbox>
	</object>
</annotation>
