<annotation>
	<folder>GrandesTrainDetector1</folder>
	<filename>smartphone_0206.jpg</filename>
	<path>\\Mac\Dropbox\zTrabajo\9 Paper Fusion OVA y OVO\BaseDatos\Train\GrandesTrainDetector1\smartphone_0206.jpg</path>
	<source>
		<database>Unknown</database>
	</source>
	<size>
		<width>1920</width>
		<height>1371</height>
		<depth>3</depth>
	</size>
	<segmented>0</segmented>
	<object>
		<name>smartphone</name>
		<pose>Unspecified</pose>
		<truncated>0</truncated>
		<difficult>0</difficult>
		<bndbox>
			<xmin>251</xmin>
			<ymin>19</ymin>
			<xmax>940</xmax>
			<ymax>1367</ymax>
		</bndbox>
	</object>
	<object>
		<name>smartphone</name>
		<pose>Unspecified</pose>
		<truncated>0</truncated>
		<difficult>0</difficult>
		<bndbox>
			<xmin>938</xmin>
			<ymin>10</ymin>
			<xmax>1685</xmax>
			<ymax>1355</ymax>
		</bndbox>
	</object>
</annotation>
