<annotation>
	<folder>train</folder>
	<filename>knife_593.jpg</filename>
	<path>C:\Users\Alcasla\Universidad\Máster Ciencia de Datos\TFM\Armas\Stage5 SSD\Datasets\train\knife_593.jpg</path>
	<source>
		<database>Unknown</database>
	</source>
	<size>
		<width>400</width>
		<height>435</height>
		<depth>3</depth>
	</size>
	<segmented>0</segmented>
	<object>
		<name>knife</name>
		<pose>Unspecified</pose>
		<truncated>0</truncated>
		<difficult>0</difficult>
		<bndbox>
			<xmin>112</xmin>
			<ymin>90</ymin>
			<xmax>318</xmax>
			<ymax>232</ymax>
		</bndbox>
	</object>
</annotation>
