<annotation>
	<folder>images</folder>
	<filename>LBbframe00421.jpg</filename>
	<path>/media/alcasla/7E78AEA50B546E1F/KnifesExpansion/Validation/images/LBbframe00421.jpg</path>
	<source>
		<database>Unknown</database>
	</source>
	<size>
		<width>1920</width>
		<height>1090</height>
		<depth>3</depth>
	</size>
	<segmented>0</segmented>
	<object>
		<name>knife</name>
		<pose>Unspecified</pose>
		<truncated>0</truncated>
		<difficult>0</difficult>
		<bndbox>
			<xmin>1256</xmin>
			<ymin>627</ymin>
			<xmax>1390</xmax>
			<ymax>751</ymax>
		</bndbox>
	</object>
</annotation>
