<annotation>
	<folder>Monederos</folder>
	<filename>monedero_1499.jpg</filename>
	<path>\\Mac\Dropbox\Monederos\monedero_1499.jpg</path>
	<source>
		<database>Unknown</database>
	</source>
	<size>
		<width>570</width>
		<height>364</height>
		<depth>3</depth>
	</size>
	<segmented>0</segmented>
	<object>
		<name>monedero</name>
		<pose>Unspecified</pose>
		<truncated>0</truncated>
		<difficult>0</difficult>
		<bndbox>
			<xmin>48</xmin>
			<ymin>4</ymin>
			<xmax>523</xmax>
			<ymax>341</ymax>
		</bndbox>
	</object>
</annotation>
