<annotation>
	<folder>GrandesTrainDetector1</folder>
	<filename>smartphone_0159.jpg</filename>
	<path>\\Mac\Dropbox\zTrabajo\9 Paper Fusion OVA y OVO\BaseDatos\Train\GrandesTrainDetector1\smartphone_0159.jpg</path>
	<source>
		<database>Unknown</database>
	</source>
	<size>
		<width>1920</width>
		<height>1280</height>
		<depth>3</depth>
	</size>
	<segmented>0</segmented>
	<object>
		<name>smartphone</name>
		<pose>Unspecified</pose>
		<truncated>0</truncated>
		<difficult>0</difficult>
		<bndbox>
			<xmin>679</xmin>
			<ymin>91</ymin>
			<xmax>1243</xmax>
			<ymax>1221</ymax>
		</bndbox>
	</object>
</annotation>
